README.rst
setup.cfg
setup.py
Markdown2PDF.egg-info/PKG-INFO
Markdown2PDF.egg-info/SOURCES.txt
Markdown2PDF.egg-info/dependency_links.txt
Markdown2PDF.egg-info/entry_points.txt
Markdown2PDF.egg-info/not-zip-safe
Markdown2PDF.egg-info/pbr.json
Markdown2PDF.egg-info/requires.txt
Markdown2PDF.egg-info/top_level.txt
markdown2pdf/__init__.py